{"is_source_file": true, "format": "TypeScript/JavaScript (TSX)", "description": "This file defines a React component named RequireAuth that enforces authentication before rendering its children. It uses hooks to access authentication state and to navigate, redirecting unauthenticated users to the login page. The component displays a loading message during auth status check and renders its children if authenticated.", "external_files": ["@/lib/auth", "next/navigation"], "external_methods": ["useAuth", "useRouter", "router.push"], "published": ["RequireAuth"], "classes": [], "methods": [{"name": "RequireAuth", "description": "React functional component that wraps children with authentication logic, redirecting unauthorized users."}], "calls": ["useAuth", "useRouter", "useEffect", "router.push"], "search-terms": ["RequireAuth", "React security", "authentication guard", "Next.js redirect", "auth check component"], "state": 2, "file_id": 29, "knowledge_revision": 62, "git_revision": "", "ctags": [], "hash": "25cda7dad0f2ad5719136a7ab8616dc1", "format-version": 4, "code-base-name": "real_estate_image_frontend", "filename": "real_estate_image_frontend/src/components/RequireAuth.tsx", "revision_history": [{"62": ""}]}