{"is_source_file": false, "format": "", "description": "", "external_files": [], "external_methods": [], "published": [], "classes": [], "methods": [], "calls": [], "search-terms": [], "state": 2, "file_id": 8, "knowledge_revision": 17, "git_revision": "95442b5005d5804d45bdcb1c027523c9a7768f4d", "hash": "0cf97a81150d3b8904f285780896980d", "format-version": 4, "code-base-name": "real_estate_image_frontend", "filename": "real_estate_image_frontend/tsconfig.json", "revision_history": [{"17": "95442b5005d5804d45bdcb1c027523c9a7768f4d"}]}